course_flow/__init__.py
course_flow/admin.py
course_flow/analytics.py
course_flow/apps.py
course_flow/asgi.py
course_flow/celery.py
course_flow/checks.py
course_flow/consumers.py
course_flow/context_processors.py
course_flow/decorators.py
course_flow/export_analytics.py
course_flow/export_functions.py
course_flow/forms.py
course_flow/import_functions.py
course_flow/lti.py
course_flow/models.py
course_flow/moodle_export.py
course_flow/redux_actions.py
course_flow/routing.py
course_flow/serializers.py
course_flow/settings.py
course_flow/tasks.py
course_flow/test_urls.py
course_flow/urls.py
course_flow/utils.py
course_flow/views.py
course_flow/locale/fr/LC_MESSAGES/django.mo
course_flow/locale/fr/LC_MESSAGES/django.po
course_flow/locale/fr/LC_MESSAGES/djangojs.mo
course_flow/locale/fr/LC_MESSAGES/djangojs.po
course_flow/management/commands/clear_orphaned_objects.py
course_flow/management/commands/create_base_disciplines.py
course_flow/management/commands/create_instances.py
course_flow/management/commands/create_saltise_strategies.py
course_flow/migrations/0001_initial.py
course_flow/migrations/0047_auto_20210315_1952.py
course_flow/migrations/0048_auto_20210315_2023.py
course_flow/migrations/0049_projectfavourite.py
course_flow/migrations/0050_workflow_disciplines.py
course_flow/migrations/0051_outcome_disciplines.py
course_flow/migrations/0052_outcomefavourite_workflowfavourite.py
course_flow/migrations/0053_auto_20210318_2131.py
course_flow/migrations/0054_auto_20210331_1748.py
course_flow/migrations/0055_delete_outcomeworkflow.py
course_flow/migrations/0056_auto_20210427_2228.py
course_flow/migrations/0057_auto_20210505_1753.py
course_flow/migrations/0058_auto_20210506_2247.py
course_flow/migrations/0059_auto_20210621_2154.py
course_flow/migrations/0060_auto_20210621_2207.py
course_flow/migrations/0061_outcomehorizontallink_degree.py
course_flow/migrations/0062_auto_20210721_1733.py
course_flow/migrations/0063_auto_20210728_2238.py
saltise_course_flow-0.8.29.dist-info/licenses/LICENSE.txt
saltise_course_flow-0.8.29.dist-info/METADATA
saltise_course_flow-0.8.29.dist-info/WHEEL
saltise_course_flow-0.8.29.dist-info/top_level.txt
saltise_course_flow-0.8.29.dist-info/RECORD
