Metadata-Version: 2.4
Name: SALTISE_course_flow
Version: 0.8.29
Summary: CourseFlow
Home-page: https://www.example.com/
Author: Arthur Ayestas Hilgert, Jeremie Choquette
Author-email: aahilgert@gmail.com
Classifier: Environment :: Web Environment
Classifier: Framework :: Django
Classifier: Framework :: Django :: 3.2
Classifier: Intended Audience :: Developers
Classifier: License :: OSI Approved :: BSD License
Classifier: Operating System :: OS Independent
Classifier: Programming Language :: Python
Classifier: Programming Language :: Python :: 3
Classifier: Programming Language :: Python :: 3 :: Only
Classifier: Programming Language :: Python :: 3.8
Classifier: Topic :: Internet :: WWW/HTTP
Classifier: Topic :: Internet :: WWW/HTTP :: Dynamic Content
Requires-Python: ~=3.8
License-File: LICENSE.txt
Requires-Dist: asgiref
Requires-Dist: bleach
Requires-Dist: celery[redis]
Requires-Dist: channels>=4
Requires-Dist: channels_redis>=4
Requires-Dist: django<4,>=3
Requires-Dist: django-compressor
Requires-Dist: django-csp
Requires-Dist: django-model-utils
Requires-Dist: django-ratelimit<4
Requires-Dist: django-redis
Requires-Dist: djangorestframework
Requires-Dist: html2text
Requires-Dist: openpyxl
Requires-Dist: pandas>=1.3.5
Requires-Dist: xlrd
Requires-Dist: xlsxwriter
Dynamic: license-file
